README
setup.py
mantis2xml/__init__.py
mantis2xml/mantis2xml.py
mantis2xml.egg-info/PKG-INFO
mantis2xml.egg-info/SOURCES.txt
mantis2xml.egg-info/dependency_links.txt
mantis2xml.egg-info/requires.txt
mantis2xml.egg-info/top_level.txt