Metadata-Version: 1.1
Name: mantis2xml
Version: 1.3
Summary: Migrates MantisBT issues to XML
Home-page: http://mantis2xml.readthedocs.org/
Author: Richard Gomes http://rgomes-info.blogspot.com
Author-email: rgomes.info@gmail.com
License: OSI Approved :: GNU General Public License v2 or later (GPLv2+)
Keywords: mantis,launchpad,migration,bugs,issue,management
Platform: UNKNOWN
Classifier: License :: OSI Approved :: GNU General Public License v2 or later (GPLv2+)
Classifier: Operating System :: OS Independent
Classifier: Programming Language :: Python
Classifier: Programming Language :: Cython
Classifier: Development Status :: 3 - Alpha
Classifier: Intended Audience :: Developers
Classifier: Environment :: Console
